spasm/__init__.py
spasm/__main__.py
spasm/_version.py
spasm/asm.py
spasmlang-0.2.1.dist-info/METADATA
spasmlang-0.2.1.dist-info/WHEEL
spasmlang-0.2.1.dist-info/entry_points.txt
spasmlang-0.2.1.dist-info/licenses/LICENSE.txt
spasmlang-0.2.1.dist-info/RECORD
