Metadata-Version: 2.1
Name: spasmlang
Version: 0.2.1
Summary: Simple Python Assembly Language
Project-URL: Documentation, https://github.com/P403n1x87/spasmlang#readme
Project-URL: Issues, https://github.com/P403n1x87/spasmlang/issues
Project-URL: Source, https://github.com/P403n1x87/spasmlang
Author-email: "Gabriele N. Tornetta" <phoenix1987@gmail.com>
License-Expression: MIT
License-File: LICENSE.txt
Keywords: assembly,development,python
Classifier: Development Status :: 4 - Beta
Classifier: Programming Language :: Python
Classifier: Programming Language :: Python :: 3.8
Classifier: Programming Language :: Python :: 3.9
Classifier: Programming Language :: Python :: 3.10
Classifier: Programming Language :: Python :: 3.11
Classifier: Programming Language :: Python :: 3.12
Classifier: Programming Language :: Python :: Implementation :: CPython
Requires-Python: >=3.8
Requires-Dist: bytecode
